mcp_server_things3/__init__.py
mcp_server_things3/applescript_handler.py
mcp_server_things3/server.py
mseep_mcp_server_things3-0.1.4.dist-info/METADATA
mseep_mcp_server_things3-0.1.4.dist-info/WHEEL
mseep_mcp_server_things3-0.1.4.dist-info/entry_points.txt
mseep_mcp_server_things3-0.1.4.dist-info/top_level.txt
mseep_mcp_server_things3-0.1.4.dist-info/RECORD
