Metadata-Version: 2.4
Name: mseep-mcp-server-things3
Version: 0.1.4
Summary: A server implementation for interacting with Things3 app on macOS through Claude AI
Author-email: mseep <support@skydeck.ai>
Requires-Python: >=3.8
Requires-Dist: mcp>=0.1.0
